odoo9_addon_pos_payment_terminal-9.0.1.0.1.99.dev13-py3.6-nspkg.pth
odoo_addons/pos_payment_terminal/README.rst
odoo_addons/pos_payment_terminal/__init__.py
odoo_addons/pos_payment_terminal/__openerp__.py
odoo_addons/pos_payment_terminal/demo/pos_payment_terminal_demo.xml
odoo_addons/pos_payment_terminal/i18n/ca.po
odoo_addons/pos_payment_terminal/i18n/es.po
odoo_addons/pos_payment_terminal/i18n/fr.po
odoo_addons/pos_payment_terminal/i18n/hr_HR.po
odoo_addons/pos_payment_terminal/i18n/it.po
odoo_addons/pos_payment_terminal/i18n/nl_NL.po
odoo_addons/pos_payment_terminal/i18n/pos_payment_terminal.pot
odoo_addons/pos_payment_terminal/models/__init__.py
odoo_addons/pos_payment_terminal/models/account_journal.py
odoo_addons/pos_payment_terminal/models/pos_config.py
odoo_addons/pos_payment_terminal/models/pos_order.py
odoo_addons/pos_payment_terminal/static/description/icon.png
odoo_addons/pos_payment_terminal/static/src/css/pos_payment_terminal.css
odoo_addons/pos_payment_terminal/static/src/js/pos_payment_terminal.js
odoo_addons/pos_payment_terminal/static/src/xml/pos_payment_terminal.xml
odoo_addons/pos_payment_terminal/tests/__init__.py
odoo_addons/pos_payment_terminal/tests/test_transactions.py
odoo_addons/pos_payment_terminal/views/account_journal.xml
odoo_addons/pos_payment_terminal/views/pos_config.xml
odoo_addons/pos_payment_terminal/views/pos_payment_terminal_template.xml
odoo9_addon_pos_payment_terminal-9.0.1.0.1.99.dev13.dist-info/METADATA
odoo9_addon_pos_payment_terminal-9.0.1.0.1.99.dev13.dist-info/WHEEL
odoo9_addon_pos_payment_terminal-9.0.1.0.1.99.dev13.dist-info/namespace_packages.txt
odoo9_addon_pos_payment_terminal-9.0.1.0.1.99.dev13.dist-info/top_level.txt
odoo9_addon_pos_payment_terminal-9.0.1.0.1.99.dev13.dist-info/RECORD
