Metadata-Version: 2.1
Name: odoo9-addon-pos-payment-terminal
Version: 9.0.1.0.1.99.dev13
Summary: Manage Payment Terminal device from POS front end
Home-page: https://github.com/OCA/pos
Author: Aurélien DUMAINE,Akretion,Odoo Community Association (OCA)
Author-email: support@odoo-community.org
License: AGPL-3
Platform: UNKNOWN
Classifier: Programming Language :: Python
Classifier: Framework :: Odoo
Classifier: License :: OSI Approved :: GNU Affero General Public License v3
Requires-Python: ~=2.7
Requires-Dist: odoo (<9.1a,>=9.0a)
